{"definitionData": {"_id": "60ad73f160e328606088b165", "entry": "gaming", "type": "as-in", "definitions": [{"isInformal": null, "isVulgar": "0", "definition": "amusement, entertainment", "pos": "noun", "synonyms": [{"similarity": "100", "isInformal": "0", "isVulgar": null, "term": "game", "targetTerm": "game", "targetSlug": "game"}, {"similarity": "100", "isInformal": "0", "isVulgar": null, "term": "sport", "targetTerm": "sport", "targetSlug": "sport"}, {"similarity": "100", "isInformal": "0", "isVulgar": null, "term": "match", "targetTerm": "match", "targetSlug": "match"}, {"similarity": "50", "isInformal": "0", "isVulgar": null, "term": "joking", "targetTerm": "joking", "targetSlug": "joking"}, {"similarity": "50", "isInformal": "0", "isVulgar": null, "term": "teasing", "targetTerm": "teasing", "targetSlug": "teasing"}, {"similarity": "50", "isInformal": "0", "isVulgar": null, "term": "pastime", "targetTerm": "pastime", "targetSlug": "pastime"}, {"similarity": "50", "isInformal": "0", "isVulgar": null, "term": "jest", "targetTerm": "jest", "targetSlug": "jest"}, {"similarity": "50", "isInformal": "0", "isVulgar": null, "term": "happiness", "targetTerm": "happiness", "targetSlug": "happiness"}, {"similarity": "50", "isInformal": "0", "isVulgar": null, "term": "prank", "targetTerm": "prank", "targetSlug": "prank"}, {"similarity": "50", "isInformal": "0", "isVulgar": null, "term": "caper", "targetTerm": "caper", "targetSlug": "caper"}, {"similarity": "50", "isInformal": "0", "isVulgar": null, "term": "humor", "targetTerm": "humor", "targetSlug": "humor"}, {"similarity": "50", "isInformal": "0", "isVulgar": null, "term": "sportiveness", "targetTerm": "sportiveness", "targetSlug": "sportiveness"}, {"similarity": "50", "isInformal": "0", "isVulgar": null, "term": "frisk", "targetTerm": "frisk", "targetSlug": "frisk"}, {"similarity": "50", "isInformal": "0", "isVulgar": null, "term": "lark", "targetTerm": "lark", "targetSlug": "lark"}, {"similarity": "50", "isInformal": "0", "isVulgar": null, "term": "frolic", "targetTerm": "frolic", "targetSlug": "frolic"}, {"similarity": "50", "isInformal": "0", "isVulgar": null, "term": "dalliance", "targetTerm": "dalliance", "targetSlug": "dalliance"}, {"similarity": "50", "isInformal": "0", "isVulgar": null, "term": "recreation", "targetTerm": "recreation", "targetSlug": "recreation"}, {"similarity": "50", "isInformal": "0", "isVulgar": null, "term": "delight", "targetTerm": "delight", "targetSlug": "delight"}, {"similarity": "50", "isInformal": "0", "isVulgar": null, "term": "diversion", "targetTerm": "diversion", "targetSlug": "diversion"}, {"similarity": "50", "isInformal": "0", "isVulgar": null, "term": "relaxation", "targetTerm": "relaxation", "targetSlug": "relaxation"}, {"similarity": "50", "isInformal": "0", "isVulgar": null, "term": "disport", "targetTerm": "disport", "targetSlug": "disport"}, {"similarity": "50", "isInformal": "0", "isVulgar": null, "term": "romp", "targetTerm": "romp", "targetSlug": "romp"}, {"similarity": "50", "isInformal": "0", "isVulgar": null, "term": "fun", "targetTerm": "fun", "targetSlug": "fun"}, {"similarity": "50", "isInformal": "0", "isVulgar": null, "term": "pleasure", "targetTerm": "pleasure", "targetSlug": "pleasure"}, {"similarity": "50", "isInformal": "0", "isVulgar": null, "term": "gambol", "targetTerm": "gambol", "targetSlug": "gambol"}, {"similarity": "50", "isInformal": "0", "isVulgar": null, "term": "foolery", "targetTerm": "foolery", "targetSlug": "foolery"}], "antonyms": [{"similarity": "-50", "isInformal": "0", "isVulgar": null, "term": "trouble", "targetTerm": "trouble", "targetSlug": "trouble"}, {"similarity": "-50", "isInformal": "0", "isVulgar": null, "term": "labor", "targetTerm": "labor", "targetSlug": "labor"}, {"similarity": "-50", "isInformal": "0", "isVulgar": null, "term": "seriousness", "targetTerm": "seriousness", "targetSlug": "seriousness"}, {"similarity": "-50", "isInformal": "0", "isVulgar": null, "term": "unhappiness", "targetTerm": "unhappiness", "targetSlug": "unhappiness"}, {"similarity": "-50", "isInformal": "0", "isVulgar": null, "term": "pain", "targetTerm": "pain", "targetSlug": "pain"}, {"similarity": "-50", "isInformal": "0", "isVulgar": null, "term": "misery", "targetTerm": "misery", "targetSlug": "misery"}, {"similarity": "-50", "isInformal": "0", "isVulgar": null, "term": "gloom", "targetTerm": "gloom", "targetSlug": "gloom"}, {"similarity": "-50", "isInformal": "0", "isVulgar": null, "term": "depression", "targetTerm": "depression", "targetSlug": "depression"}, {"similarity": "-50", "isInformal": "0", "isVulgar": null, "term": "work", "targetTerm": "work", "targetSlug": "work"}, {"similarity": "-50", "isInformal": "0", "isVulgar": null, "term": "profession", "targetTerm": "profession", "targetSlug": "profession"}, {"similarity": "-10", "isInformal": "0", "isVulgar": null, "term": "extreme", "targetTerm": "extreme", "targetSlug": "extreme"}, {"similarity": "-50", "isInformal": "0", "isVulgar": null, "term": "melancholy", "targetTerm": "melancholy", "targetSlug": "melancholy"}, {"similarity": "-50", "isInformal": "0", "isVulgar": null, "term": "sorrow", "targetTerm": "sorrow", "targetSlug": "sorrow"}, {"similarity": "-50", "isInformal": "0", "isVulgar": null, "term": "sadness", "targetTerm": "sadness", "targetSlug": "sadness"}, {"similarity": "-50", "isInformal": "0", "isVulgar": null, "term": "task", "targetTerm": "task", "targetSlug": "task"}], "note": null, "targetId": "14012", "targetTerm": "play"}, {"isInformal": null, "isVulgar": "0", "definition": "lottery for a prize", "pos": "noun", "synonyms": [{"similarity": "100", "isInformal": "0", "isVulgar": null, "term": "game of chance", "targetTerm": "game of chance", "targetSlug": "game%20of%20chance"}, {"similarity": "50", "isInformal": "0", "isVulgar": null, "term": "draw", "targetTerm": "draw", "targetSlug": "draw"}, {"similarity": "50", "isInformal": "0", "isVulgar": null, "term": "flier", "targetTerm": "flier", "targetSlug": "flier"}, {"similarity": "50", "isInformal": "0", "isVulgar": null, "term": "pool", "targetTerm": "pool", "targetSlug": "pool"}, {"similarity": "50", "isInformal": "0", "isVulgar": null, "term": "stake", "targetTerm": "stake", "targetSlug": "stake"}, {"similarity": "50", "isInformal": "0", "isVulgar": null, "term": "sweep", "targetTerm": "sweep", "targetSlug": "sweep"}, {"similarity": "50", "isInformal": "1", "isVulgar": null, "term": "lots", "targetTerm": "lots", "targetSlug": "lots"}, {"similarity": "50", "isInformal": "0", "isVulgar": null, "term": "disposition", "targetTerm": "disposition", "targetSlug": "disposition"}, {"similarity": "50", "isInformal": "0", "isVulgar": null, "term": "gambling", "targetTerm": "gambling", "targetSlug": "gambling"}, {"similarity": "50", "isInformal": "0", "isVulgar": null, "term": "speculation", "targetTerm": "speculation", "targetSlug": "speculation"}, {"similarity": "50", "isInformal": "0", "isVulgar": null, "term": "wager", "targetTerm": "wager", "targetSlug": "wager"}, {"similarity": "50", "isInformal": "0", "isVulgar": null, "term": "drawing", "targetTerm": "drawing", "targetSlug": "drawing"}, {"similarity": "50", "isInformal": "0", "isVulgar": null, "term": "bet", "targetTerm": "bet", "targetSlug": "bet"}, {"similarity": "100", "isInformal": "0", "isVulgar": null, "term": "betting", "targetTerm": "betting", "targetSlug": "betting"}, {"similarity": "100", "isInformal": "0", "isVulgar": null, "term": "sweepstake", "targetTerm": "sweepstake", "targetSlug": "sweepstake"}, {"similarity": "50", "isInformal": "0", "isVulgar": null, "term": "tossup", "targetTerm": "tossup", "targetSlug": "tossup"}, {"similarity": "50", "isInformal": "0", "isVulgar": null, "term": "wagering", "targetTerm": "wagering", "targetSlug": "complex"}, {"similarity": "50", "isInformal": "0", "isVulgar": null, "term": "numbers", "targetTerm": "numbers", "targetSlug": "numbers"}, {"similarity": "10", "isInformal": "0", "isVulgar": null, "term": "long odds", "targetTerm": "long odds", "targetSlug": "long%20odds"}, {"similarity": "10", "isInformal": "0", "isVulgar": null, "term": "numbers game", "targetTerm": "numbers game", "targetSlug": "numbers%20game"}, {"similarity": "10", "isInformal": "0", "isVulgar": null, "term": "random shot", "targetTerm": "random shot", "targetSlug": "random%20shot"}], "antonyms": [], "note": null, "targetId": "15016", "targetTerm": "raffle"}, {"isInformal": null, "isVulgar": "0", "definition": "betting", "pos": "noun", "synonyms": [{"similarity": "100", "isInformal": "1", "isVulgar": null, "term": "action", "targetTerm": "action", "targetSlug": "action"}, {"similarity": "50", "isInformal": "0", "isVulgar": null, "term": "speculation", "targetTerm": "speculation", "targetSlug": "speculation"}, {"similarity": "50", "isInformal": "0", "isVulgar": null, "term": "staking", "targetTerm": null, "targetSlug": null}, {"similarity": "10", "isInformal": "0", "isVulgar": null, "term": "laying odds", "targetTerm": "laying odds", "targetSlug": "laying%20odds"}], "antonyms": [], "note": null, "targetId": "21259", "targetTerm": "gambling"}, {"isInformal": null, "isVulgar": "0", "definition": "bet, wager", "pos": "verb", "synonyms": [{"similarity": "100", "isInformal": "0", "isVulgar": null, "term": "play", "targetTerm": "play", "targetSlug": "play"}, {"similarity": "50", "isInformal": "0", "isVulgar": null, "term": "game", "targetTerm": "game", "targetSlug": "game"}, {"similarity": "50", "isInformal": "0", "isVulgar": null, "term": "stake", "targetTerm": "stake", "targetSlug": "stake"}, {"similarity": "50", "isInformal": "0", "isVulgar": null, "term": "gamble", "targetTerm": "gamble", "targetSlug": "gamble"}, {"similarity": "50", "isInformal": "0", "isVulgar": null, "term": "hazard", "targetTerm": "hazard", "targetSlug": "hazard"}, {"similarity": "50", "isInformal": "0", "isVulgar": null, "term": "risk", "targetTerm": "risk", "targetSlug": "risk"}, {"similarity": "10", "isInformal": "0", "isVulgar": null, "term": "give odds", "targetTerm": "give odds", "targetSlug": "give%20odds"}], "antonyms": [{"similarity": "-10", "isInformal": "0", "isVulgar": null, "term": "rough", "targetTerm": "rough", "targetSlug": "rough"}, {"similarity": "-10", "isInformal": "0", "isVulgar": null, "term": "neglect", "targetTerm": "neglect", "targetSlug": "neglect"}, {"similarity": "-10", "isInformal": "0", "isVulgar": null, "term": "take", "targetTerm": "take", "targetSlug": "take"}, {"similarity": "-10", "isInformal": "0", "isVulgar": null, "term": "lift", "targetTerm": "lift", "targetSlug": "lift"}], "note": null, "targetId": "11049", "targetTerm": "lay"}, {"isInformal": null, "isVulgar": "0", "definition": "gamble, risk", "pos": "verb", "synonyms": [{"similarity": "100", "isInformal": "0", "isVulgar": null, "term": "put", "targetTerm": "put", "targetSlug": "put"}, {"similarity": "100", "isInformal": "0", "isVulgar": null, "term": "game", "targetTerm": "game", "targetSlug": "game"}, {"similarity": "100", "isInformal": "0", "isVulgar": null, "term": "set", "targetTerm": "set", "targetSlug": "set"}, {"similarity": "100", "isInformal": "0", "isVulgar": null, "term": "take", "targetTerm": "take", "targetSlug": "take"}, {"similarity": "50", "isInformal": "0", "isVulgar": null, "term": "maneuver", "targetTerm": "maneuver", "targetSlug": "maneuver"}, {"similarity": "50", "isInformal": "0", "isVulgar": null, "term": "speculate", "targetTerm": "speculate", "targetSlug": "speculate"}, {"similarity": "50", "isInformal": "0", "isVulgar": null, "term": "jockey", "targetTerm": "jockey", "targetSlug": "jockey"}, {"similarity": "50", "isInformal": "0", "isVulgar": null, "term": "finesse", "targetTerm": "finesse", "targetSlug": "finesse"}, {"similarity": "50", "isInformal": "0", "isVulgar": null, "term": "stake", "targetTerm": "stake", "targetSlug": "stake"}, {"similarity": "50", "isInformal": "0", "isVulgar": null, "term": "chance", "targetTerm": "chance", "targetSlug": "chance"}, {"similarity": "50", "isInformal": "0", "isVulgar": null, "term": "hazard", "targetTerm": "hazard", "targetSlug": "hazard"}, {"similarity": "50", "isInformal": "0", "isVulgar": null, "term": "exploit", "targetTerm": "exploit", "targetSlug": "exploit"}, {"similarity": "50", "isInformal": "0", "isVulgar": null, "term": "bet", "targetTerm": "bet", "targetSlug": "bet"}, {"similarity": "50", "isInformal": "0", "isVulgar": null, "term": "wager", "targetTerm": "wager", "targetSlug": "wager"}, {"similarity": "50", "isInformal": "0", "isVulgar": null, "term": "manipulate", "targetTerm": "manipulate", "targetSlug": "manipulate"}, {"similarity": "10", "isInformal": "0", "isVulgar": null, "term": "lay money on", "targetTerm": "lay money on", "targetSlug": "lay%20money%20on"}], "antonyms": [{"similarity": "-10", "isInformal": "0", "isVulgar": null, "term": "direct", "targetTerm": "direct", "targetSlug": "direct"}, {"similarity": "-10", "isInformal": "0", "isVulgar": null, "term": "watch", "targetTerm": "watch", "targetSlug": "watch"}, {"similarity": "-10", "isInformal": "0", "isVulgar": null, "term": "work", "targetTerm": "work", "targetSlug": "work"}, {"similarity": "-50", "isInformal": "0", "isVulgar": null, "term": "leave alone", "targetTerm": "leave alone", "targetSlug": "leave%20alone"}, {"similarity": "-50", "isInformal": "0", "isVulgar": null, "term": "neglect", "targetTerm": "neglect", "targetSlug": "neglect"}, {"similarity": "-100", "isInformal": "0", "isVulgar": null, "term": "displace", "targetTerm": "displace", "targetSlug": "displace"}, {"similarity": "-100", "isInformal": "0", "isVulgar": null, "term": "remove", "targetTerm": "remove", "targetSlug": "remove"}, {"similarity": "-10", "isInformal": "0", "isVulgar": null, "term": "listen", "targetTerm": "listen", "targetSlug": "listen"}], "note": null, "targetId": "14017", "targetTerm": "play"}, {"isInformal": null, "isVulgar": "0", "definition": "bet, wager", "pos": "verb", "synonyms": [{"similarity": "50", "isInformal": "0", "isVulgar": null, "term": "chance", "targetTerm": "chance", "targetSlug": "chance"}, {"similarity": "50", "isInformal": "0", "isVulgar": null, "term": "play", "targetTerm": "play", "targetSlug": "play"}, {"similarity": "50", "isInformal": "0", "isVulgar": null, "term": "set", "targetTerm": "set", "targetSlug": "set"}, {"similarity": "50", "isInformal": "0", "isVulgar": null, "term": "risk", "targetTerm": "risk", "targetSlug": "risk"}, {"similarity": "50", "isInformal": "0", "isVulgar": null, "term": "jeopardize", "targetTerm": "jeopardize", "targetSlug": "jeopardize"}, {"similarity": "50", "isInformal": "0", "isVulgar": null, "term": "back", "targetTerm": "back", "targetSlug": "back"}, {"similarity": "50", "isInformal": "0", "isVulgar": null, "term": "hazard", "targetTerm": "hazard", "targetSlug": "hazard"}, {"similarity": "50", "isInformal": "0", "isVulgar": null, "term": "grubstake", "targetTerm": "grubstake", "targetSlug": "grubstake"}, {"similarity": "50", "isInformal": "0", "isVulgar": null, "term": "game", "targetTerm": "game", "targetSlug": "game"}, {"similarity": "50", "isInformal": "0", "isVulgar": null, "term": "bankroll", "targetTerm": "bankroll", "targetSlug": "bankroll"}, {"similarity": "50", "isInformal": "0", "isVulgar": null, "term": "lay", "targetTerm": "lay", "targetSlug": "lay"}, {"similarity": "50", "isInformal": "0", "isVulgar": null, "term": "venture", "targetTerm": "venture", "targetSlug": "venture"}, {"similarity": "50", "isInformal": "0", "isVulgar": null, "term": "put", "targetTerm": "put", "targetSlug": "put"}, {"similarity": "50", "isInformal": "0", "isVulgar": null, "term": "finance", "targetTerm": "finance", "targetSlug": "finance"}, {"similarity": "50", "isInformal": "0", "isVulgar": null, "term": "capitalize", "targetTerm": "capitalize", "targetSlug": "capitalize"}, {"similarity": "50", "isInformal": "0", "isVulgar": null, "term": "imperil", "targetTerm": "imperil", "targetSlug": "imperil"}, {"similarity": "50", "isInformal": "0", "isVulgar": null, "term": "gamble", "targetTerm": "gamble", "targetSlug": "gamble"}, {"similarity": "50", "isInformal": "0", "isVulgar": null, "term": "pledge", "targetTerm": "pledge", "targetSlug": "pledge"}, {"similarity": "10", "isInformal": "0", "isVulgar": null, "term": "put on", "targetTerm": "put on", "targetSlug": "put%20on"}, {"similarity": "10", "isInformal": "0", "isVulgar": null, "term": "stake down", "targetTerm": "stake down", "targetSlug": "stake%20down"}], "antonyms": [{"similarity": "-50", "isInformal": "0", "isVulgar": null, "term": "take", "targetTerm": "take", "targetSlug": "take"}, {"similarity": "-50", "isInformal": "0", "isVulgar": null, "term": "discourage", "targetTerm": "discourage", "targetSlug": "discourage"}, {"similarity": "-50", "isInformal": "0", "isVulgar": null, "term": "remove", "targetTerm": "remove", "targetSlug": "remove"}, {"similarity": "-50", "isInformal": "0", "isVulgar": null, "term": "displace", "targetTerm": "displace", "targetSlug": "displace"}, {"similarity": "-50", "isInformal": "0", "isVulgar": null, "term": "plan", "targetTerm": "plan", "targetSlug": "plan"}, {"similarity": "-50", "isInformal": "0", "isVulgar": null, "term": "design", "targetTerm": "design", "targetSlug": "design"}, {"similarity": "-50", "isInformal": "0", "isVulgar": null, "term": "guard", "targetTerm": "guard", "targetSlug": "guard"}, {"similarity": "-50", "isInformal": "0", "isVulgar": null, "term": "dissuade", "targetTerm": "dissuade", "targetSlug": "dissuade"}], "note": null, "targetId": "17384", "targetTerm": "stake"}, {"isInformal": null, "isVulgar": "0", "definition": "bet money or something else in a gamble", "pos": "verb", "synonyms": [{"similarity": "100", "isInformal": "0", "isVulgar": null, "term": "speculate", "targetTerm": "speculate", "targetSlug": "speculate"}, {"similarity": "100", "isInformal": "0", "isVulgar": null, "term": "put up", "targetTerm": "put up", "targetSlug": "put%20up"}, {"similarity": "100", "isInformal": "0", "isVulgar": null, "term": "gamble", "targetTerm": "gamble", "targetSlug": "gamble"}, {"similarity": "50", "isInformal": "1", "isVulgar": null, "term": "shoot", "targetTerm": "shoot", "targetSlug": "shoot"}, {"similarity": "50", "isInformal": "0", "isVulgar": null, "term": "play", "targetTerm": "play", "targetSlug": "play"}, {"similarity": "50", "isInformal": "1", "isVulgar": null, "term": "set", "targetTerm": "set", "targetSlug": "set"}, {"similarity": "50", "isInformal": "0", "isVulgar": null, "term": "pledge", "targetTerm": "pledge", "targetSlug": "pledge"}, {"similarity": "50", "isInformal": "0", "isVulgar": null, "term": "lay", "targetTerm": "lay", "targetSlug": "lay"}, {"similarity": "50", "isInformal": "0", "isVulgar": null, "term": "stake", "targetTerm": "stake", "targetSlug": "stake"}, {"similarity": "50", "isInformal": "0", "isVulgar": null, "term": "chance", "targetTerm": "chance", "targetSlug": "chance"}, {"similarity": "50", "isInformal": "0", "isVulgar": null, "term": "hazard", "targetTerm": "hazard", "targetSlug": "hazard"}, {"similarity": "50", "isInformal": "0", "isVulgar": null, "term": "game", "targetTerm": "game", "targetSlug": "game"}, {"similarity": "50", "isInformal": "0", "isVulgar": null, "term": "plunge", "targetTerm": "plunge", "targetSlug": "plunge"}, {"similarity": "50", "isInformal": "0", "isVulgar": null, "term": "adventure", "targetTerm": "adventure", "targetSlug": "adventure"}, {"similarity": "50", "isInformal": "0", "isVulgar": null, "term": "venture", "targetTerm": "venture", "targetSlug": "venture"}, {"similarity": "50", "isInformal": "0", "isVulgar": null, "term": "hedge", "targetTerm": "hedge", "targetSlug": "hedge"}, {"similarity": "50", "isInformal": "0", "isVulgar": null, "term": "parlay", "targetTerm": "parlay", "targetSlug": "parlay"}, {"similarity": "50", "isInformal": "0", "isVulgar": null, "term": "risk", "targetTerm": "risk", "targetSlug": "risk"}, {"similarity": "50", "isInformal": "0", "isVulgar": null, "term": "hustle", "targetTerm": "hustle", "targetSlug": "hustle"}, {"similarity": "10", "isInformal": "1", "isVulgar": null, "term": "put on", "targetTerm": "put on", "targetSlug": "put%20on"}, {"similarity": "50", "isInformal": "0", "isVulgar": null, "term": "spec", "targetTerm": "spec", "targetSlug": "spec"}, {"similarity": "10", "isInformal": "0", "isVulgar": null, "term": "lay a wager", "targetTerm": "lay a wager", "targetSlug": "lay%20a%20wager"}, {"similarity": "10", "isInformal": "0", "isVulgar": null, "term": "play the market", "targetTerm": "play the market", "targetSlug": "play%20the%20market"}, {"similarity": "10", "isInformal": "0", "isVulgar": null, "term": "put on the line", "targetTerm": "put on the line", "targetSlug": "put%20on%20the%20line"}, {"similarity": "10", "isInformal": "0", "isVulgar": null, "term": "shoot the works", "targetTerm": "shoot the works", "targetSlug": "shoot%20the%20works"}, {"similarity": "10", "isInformal": "0", "isVulgar": null, "term": "take action", "targetTerm": "take action", "targetSlug": "take%20action"}], "antonyms": [{"similarity": "-50", "isInformal": "0", "isVulgar": null, "term": "rise", "targetTerm": "rise", "targetSlug": "rise"}, {"similarity": "-50", "isInformal": "0", "isVulgar": null, "term": "ascend", "targetTerm": "ascend", "targetSlug": "ascend"}], "note": null, "targetId": "19627", "targetTerm": "wager"}, {"isInformal": null, "isVulgar": "0", "definition": "gamble", "pos": "verb", "synonyms": [{"similarity": "100", "isInformal": "0", "isVulgar": null, "term": "speculate", "targetTerm": "speculate", "targetSlug": "speculate"}, {"similarity": "100", "isInformal": "0", "isVulgar": null, "term": "wager", "targetTerm": "wager", "targetSlug": "wager"}, {"similarity": "50", "isInformal": "0", "isVulgar": null, "term": "set", "targetTerm": "set", "targetSlug": "set"}, {"similarity": "50", "isInformal": "0", "isVulgar": null, "term": "chance", "targetTerm": "chance", "targetSlug": "chance"}, {"similarity": "50", "isInformal": "0", "isVulgar": null, "term": "hazard", "targetTerm": "hazard", "targetSlug": "hazard"}, {"similarity": "50", "isInformal": "0", "isVulgar": null, "term": "put", "targetTerm": "put", "targetSlug": "put"}, {"similarity": "50", "isInformal": "0", "isVulgar": null, "term": "game", "targetTerm": "game", "targetSlug": "game"}, {"similarity": "50", "isInformal": "0", "isVulgar": null, "term": "venture", "targetTerm": "venture", "targetSlug": "venture"}, {"similarity": "50", "isInformal": "0", "isVulgar": null, "term": "ante", "targetTerm": "ante", "targetSlug": "ante"}, {"similarity": "50", "isInformal": "0", "isVulgar": null, "term": "trust", "targetTerm": "trust", "targetSlug": "trust"}, {"similarity": "50", "isInformal": "0", "isVulgar": null, "term": "risk", "targetTerm": "risk", "targetSlug": "risk"}, {"similarity": "50", "isInformal": "0", "isVulgar": null, "term": "pledge", "targetTerm": "pledge", "targetSlug": "pledge"}, {"similarity": "100", "isInformal": "0", "isVulgar": null, "term": "pony up", "targetTerm": "pony up", "targetSlug": "pony%20up"}, {"similarity": "50", "isInformal": "0", "isVulgar": null, "term": "dice", "targetTerm": "dice", "targetSlug": "dice"}, {"similarity": "10", "isInformal": "0", "isVulgar": null, "term": "buy in on", "targetTerm": "buy in on", "targetSlug": "buy%20in%20on"}, {"similarity": "10", "isInformal": "0", "isVulgar": null, "term": "lay down", "targetTerm": "lay down", "targetSlug": "lay%20down"}, {"similarity": "10", "isInformal": "0", "isVulgar": null, "term": "lay odds", "targetTerm": "lay odds", "targetSlug": "lay%20odds"}, {"similarity": "10", "isInformal": "0", "isVulgar": null, "term": "play against", "targetTerm": "play against", "targetSlug": "play%20against"}, {"similarity": "10", "isInformal": "0", "isVulgar": null, "term": "play for", "targetTerm": "play for", "targetSlug": "play%20for"}, {"similarity": "10", "isInformal": "0", "isVulgar": null, "term": "play the ponies", "targetTerm": "play the ponies", "targetSlug": "play%20the%20ponies"}, {"similarity": "10", "isInformal": "0", "isVulgar": null, "term": "put money on", "targetTerm": "put money on", "targetSlug": "put%20money%20on"}, {"similarity": "10", "isInformal": "0", "isVulgar": null, "term": "tempt fortune", "targetTerm": "tempt fortune", "targetSlug": "tempt%20fortune"}, {"similarity": "10", "isInformal": "0", "isVulgar": null, "term": "toss up", "targetTerm": "toss up", "targetSlug": "toss%20up"}], "antonyms": [{"similarity": "-50", "isInformal": "0", "isVulgar": null, "term": "remove", "targetTerm": "remove", "targetSlug": "remove"}, {"similarity": "-50", "isInformal": "0", "isVulgar": null, "term": "displace", "targetTerm": "displace", "targetSlug": "displace"}], "note": null, "targetId": "1983", "targetTerm": "bet"}, {"isInformal": null, "isVulgar": "0", "definition": "take a chance on winning", "pos": "verb", "synonyms": [{"similarity": "100", "isInformal": "0", "isVulgar": null, "term": "speculate", "targetTerm": "speculate", "targetSlug": "speculate"}, {"similarity": "100", "isInformal": "0", "isVulgar": null, "term": "wager", "targetTerm": "wager", "targetSlug": "wager"}, {"similarity": "100", "isInformal": "0", "isVulgar": null, "term": "bet", "targetTerm": "bet", "targetSlug": "bet"}, {"similarity": "50", "isInformal": "0", "isVulgar": null, "term": "play", "targetTerm": "play", "targetSlug": "play"}, {"similarity": "50", "isInformal": "0", "isVulgar": null, "term": "jeopardize", "targetTerm": "jeopardize", "targetSlug": "jeopardize"}, {"similarity": "50", "isInformal": "0", "isVulgar": null, "term": "brave", "targetTerm": "brave", "targetSlug": "brave"}, {"similarity": "50", "isInformal": "0", "isVulgar": null, "term": "risk", "targetTerm": "risk", "targetSlug": "risk"}, {"similarity": "50", "isInformal": "0", "isVulgar": null, "term": "challenge", "targetTerm": "challenge", "targetSlug": "challenge"}, {"similarity": "50", "isInformal": "0", "isVulgar": null, "term": "stake", "targetTerm": "stake", "targetSlug": "stake"}, {"similarity": "50", "isInformal": "0", "isVulgar": null, "term": "back", "targetTerm": "back", "targetSlug": "back"}, {"similarity": "50", "isInformal": "0", "isVulgar": null, "term": "hazard", "targetTerm": "hazard", "targetSlug": "hazard"}, {"similarity": "50", "isInformal": "0", "isVulgar": null, "term": "face", "targetTerm": "face", "targetSlug": "face"}, {"similarity": "50", "isInformal": "0", "isVulgar": null, "term": "lot", "targetTerm": "lot", "targetSlug": "lot"}, {"similarity": "50", "isInformal": "0", "isVulgar": null, "term": "endanger", "targetTerm": "endanger", "targetSlug": "endanger"}, {"similarity": "50", "isInformal": "0", "isVulgar": null, "term": "game", "targetTerm": "game", "targetSlug": "game"}, {"similarity": "50", "isInformal": "0", "isVulgar": null, "term": "set", "targetTerm": "set", "targetSlug": "set"}, {"similarity": "50", "isInformal": "0", "isVulgar": null, "term": "venture", "targetTerm": "venture", "targetSlug": "venture"}, {"similarity": "50", "isInformal": "0", "isVulgar": null, "term": "put", "targetTerm": "put", "targetSlug": "put"}, {"similarity": "50", "isInformal": "0", "isVulgar": null, "term": "plunge", "targetTerm": "plunge", "targetSlug": "plunge"}, {"similarity": "50", "isInformal": "0", "isVulgar": null, "term": "defy", "targetTerm": "defy", "targetSlug": "defy"}, {"similarity": "50", "isInformal": "0", "isVulgar": null, "term": "dare", "targetTerm": "dare", "targetSlug": "dare"}, {"similarity": "50", "isInformal": "0", "isVulgar": null, "term": "imperil", "targetTerm": "imperil", "targetSlug": "imperil"}, {"similarity": "10", "isInformal": "0", "isVulgar": null, "term": "cast lots", "targetTerm": "cast lots", "targetSlug": "cast%20lots"}, {"similarity": "10", "isInformal": "0", "isVulgar": null, "term": "buck the odds", "targetTerm": "buck the odds", "targetSlug": "buck%20the%20odds"}, {"similarity": "10", "isInformal": "0", "isVulgar": null, "term": "cut the cards", "targetTerm": "cut the cards", "targetSlug": "cut%20the%20cards"}, {"similarity": "10", "isInformal": "0", "isVulgar": null, "term": "flip the coin", "targetTerm": "flip the coin", "targetSlug": "flip%20the%20coin"}, {"similarity": "10", "isInformal": "0", "isVulgar": null, "term": "go for broke", "targetTerm": "go for broke", "targetSlug": "go%20for%20broke"}, {"similarity": "10", "isInformal": "0", "isVulgar": null, "term": "lay money on", "targetTerm": "lay money on", "targetSlug": "lay%20money%20on"}, {"similarity": "10", "isInformal": "0", "isVulgar": null, "term": "make a bet", "targetTerm": "make a bet", "targetSlug": "make%20a%20bet"}, {"similarity": "10", "isInformal": "0", "isVulgar": null, "term": "put faith in", "targetTerm": "put faith in", "targetSlug": "put%20faith%20in"}, {"similarity": "10", "isInformal": "0", "isVulgar": null, "term": "put trust in", "targetTerm": "put trust in", "targetSlug": "put%20trust%20in"}, {"similarity": "10", "isInformal": "0", "isVulgar": null, "term": "shoot the moon", "targetTerm": "shoot the moon", "targetSlug": "shoot%20the%20moon"}, {"similarity": "10", "isInformal": "0", "isVulgar": null, "term": "shoot the works", "targetTerm": "shoot the works", "targetSlug": "shoot%20the%20works"}, {"similarity": "10", "isInformal": "0", "isVulgar": null, "term": "take a flyer", "targetTerm": "take a flyer", "targetSlug": "take%20a%20flyer"}, {"similarity": "10", "isInformal": "0", "isVulgar": null, "term": "tempt fortune", "targetTerm": "tempt fortune", "targetSlug": "tempt%20fortune"}, {"similarity": "10", "isInformal": "0", "isVulgar": null, "term": "trust to luck", "targetTerm": "trust to luck", "targetSlug": "trust%20to%20luck"}, {"similarity": "10", "isInformal": "0", "isVulgar": null, "term": "stick one's neck out", "targetTerm": "stick one's neck out", "targetSlug": "stick%20one%27s%20neck%20out"}, {"similarity": "10", "isInformal": "0", "isVulgar": null, "term": "try one's luck", "targetTerm": "try one's luck", "targetSlug": "try%20one%27s%20luck"}], "antonyms": [{"similarity": "-10", "isInformal": "0", "isVulgar": null, "term": "plan", "targetTerm": "plan", "targetSlug": "plan"}, {"similarity": "-10", "isInformal": "0", "isVulgar": null, "term": "design", "targetTerm": "design", "targetSlug": "design"}, {"similarity": "-10", "isInformal": "0", "isVulgar": null, "term": "be careful", "targetTerm": "be careful", "targetSlug": "be%20careful"}, {"similarity": "-50", "isInformal": "0", "isVulgar": null, "term": "rise", "targetTerm": "rise", "targetSlug": "rise"}, {"similarity": "-50", "isInformal": "0", "isVulgar": null, "term": "remove", "targetTerm": "remove", "targetSlug": "remove"}, {"similarity": "-50", "isInformal": "0", "isVulgar": null, "term": "displace", "targetTerm": "displace", "targetSlug": "displace"}, {"similarity": "-50", "isInformal": "0", "isVulgar": null, "term": "save", "targetTerm": "save", "targetSlug": "save"}, {"similarity": "-50", "isInformal": "0", "isVulgar": null, "term": "discourage", "targetTerm": "discourage", "targetSlug": "discourage"}, {"similarity": "-10", "isInformal": "0", "isVulgar": null, "term": "safeguard", "targetTerm": "safeguard", "targetSlug": "safeguard"}, {"similarity": "-10", "isInformal": "0", "isVulgar": null, "term": "insure", "targetTerm": "insure", "targetSlug": "insure"}, {"similarity": "-10", "isInformal": "0", "isVulgar": null, "term": "guard", "targetTerm": "guard", "targetSlug": "guard"}, {"similarity": "-10", "isInformal": "0", "isVulgar": null, "term": "ensure", "targetTerm": "ensure", "targetSlug": "ensure"}, {"similarity": "-50", "isInformal": "0", "isVulgar": null, "term": "ascend", "targetTerm": "ascend", "targetSlug": "ascend"}, {"similarity": "-50", "isInformal": "0", "isVulgar": null, "term": "dissuade", "targetTerm": "dissuade", "targetSlug": "dissuade"}, {"similarity": "-50", "isInformal": "0", "isVulgar": null, "term": "hide", "targetTerm": "hide", "targetSlug": "hide"}], "note": null, "targetId": "8514", "targetTerm": "gamble"}], "slug": "gaming"}, "inflections": [{"displayForm": "gamings", "slug": "gamings"}], "pronunciation": {"ipa": "\u02c8ge\u026a m\u026a\u014b ", "spell": "<span class=\"bold\">gey</span>-ming ", "audio": {"audio/ogg": "https://static.sfdict.com/audio/lunawav/G00/G0037700.ogg", "audio/mpeg": "https://static.sfdict.com/audio/G00/G0037700.mp3"}}, "confusables": [], "supplementaryNotes": [], "etymology": [], "exampleSentences": [{"source": {"url": "http://feedproxy.google.com/~r/Techcrunch/~3/OmK4giN_nGw/", "publication_date": "2020-08-28T15:07:02Z", "author": "Connie Loizos", "source_name": "TechCrunch", "title": "Laura Deming, Frederik Groce, Amish Jani, Jessica Verrilli and Vanessa Larco are coming to Disrupt", "type": "const", "abbreviation": "nlp"}, "profanity": 0, "id": 36366083, "sentence": "Today, the Georgia Tech grad says her passion for design and analytics stems from those days spent in both the gaming industry and focused on productivity apps."}, {"source": {"url": "https://www.popsci.com/story/shop/monitor-arms-for-your-desk/", "publication_date": "2020-08-26T19:04:03Z", "author": "PopSci Commerce Team", "source_name": "Popular Science", "title": "The best monitor arms for desk-mounting your display", "type": "const", "abbreviation": "nlp"}, "profanity": 0, "id": 36370880, "sentence": "For gaming setups, creative studios, and even traditional offices, a dual-monitor setup is a great way to boost efficiency, and if you\u2019ve got the space, this is the arm for the job."}, {"source": {"url": "https://freakonomics.com/podcast/sports-gambling-rebroadcast/", "publication_date": "2020-08-20T03:00:16Z", "author": "Stephen J. Dubner", "source_name": "Freakonomics", "title": "The Economics of Sports Gambling (Ep. 388 Rebroadcast)", "type": "const", "abbreviation": "nlp"}, "profanity": 0, "id": 36374268, "sentence": "I\u2019ve done a lot of research on lotteries and other types of gaming."}, {"source": {"url": "https://www.technologyreview.com/2020/08/18/1006217/the-minecraft-institvte-of-technology/", "publication_date": "2020-08-19T03:55:00Z", "author": "Tate Ryan-Mosley", "source_name": "MIT Technology Review", "title": "The Minecraft Institvte of Technology", "type": "const", "abbreviation": "nlp"}, "profanity": 0, "id": 36368385, "sentence": "Given that most of us working on this have a background in computing rather than e-sports or gaming, we put a lot of thought into the computing structure and developed new features for the Minecraft server."}, {"source": {"url": "https://www.ozy.com/opinion/virtually-celebrate-in-style/357277/?utm_source=rss&utm_medium=rss&utm_campaign=virtually-celebrate-in-style", "publication_date": "2020-08-05T05:42:00Z", "author": "Tracy Moran", "source_name": "Ozy", "title": "Virtually Celebrate in Style", "type": "const", "abbreviation": "nlp"}, "profanity": 0, "id": 36394432, "sentence": "This got me looking into what gaming options are available, and there are A LOT."}, {"source": {"url": "https://singularityhub.com/2020/05/24/epic-games-insane-video-game-graphics-demo-explained-in-simple-terms/", "publication_date": "2020-05-24T14:00:37Z", "author": "Aaron Frank", "source_name": "Singularity Hub\u00a0", "title": "Epic Games\u2019 Insane Video Game Graphics Demo Explained in Simple Terms", "type": "const", "abbreviation": "nlp"}, "profanity": 0, "id": 36395499, "sentence": "The current generation of gaming consoles, including Sony\u2019s PlayStation 4 and Microsoft\u2019s Xbox One, are now using seven-year-old hardware technologies, first released in 2013."}, {"source": {"url": "https://www.searchenginewatch.com/2020/05/21/what-are-pbns-and-should-you-use-them/", "publication_date": "2020-05-21T13:10:15Z", "author": "Tudor Lodge Consultants", "source_name": "Search Engine Watch", "title": "What are PBNs and should you use them?", "type": "const", "abbreviation": "nlp"}, "profanity": 0, "id": 36397954, "sentence": "However, over the last few years, Google has started to penalize any PBN site and who they link to, considering this a quick gaming of the system and anti-Google guidelines."}, {"sentence": "It was at this parliament that the famous acts against horse racing and deceitful gaming were passed.", "profanity": 0, "source": {"title": "The Every Day Book of History and Chronology", "type": "const", "url": "http://www.gutenberg.org/files/44028/44028-h/44028-h.htm", "author": "Joel Munsell", "publication_date": null, "abbreviation": "gbg"}, "id": "pncqLncBoaa-DHVhCdIT"}, {"sentence": "Aristide caught him by the collar as he stood on the covered terrace, a foot or two from the threshold of the gaming-room.", "profanity": 0, "source": {"title": "The Joyous Adventures of Aristide Pujol", "type": "const", "url": "http://www.gutenberg.org/files/26154/26154-h/26154-h.htm", "author": "William J. Locke", "publication_date": null, "abbreviation": "gbg"}, "id": "YHgqLncBoaa-DHVhFRYm"}, {"sentence": "Excellent company; a frequenter of the home of Mme. de la Baudraye, where he satisfied his penchant for gaming.", "profanity": 0, "source": {"title": "Repertory Of The Comedie Humaine, Complete, A -- Z", "type": "const", "url": "http://www.gutenberg.org/files/17635/17635-h/17635-h.htm", "author": "Anatole Cerfberr and Jules Franois Christophe", "publication_date": null, "abbreviation": "gbg"}, "id": "jXgqLncBoaa-DHVhcVlE"}], "slugLuna": "gaming"}