{"definitionData": {"_id": "60ad738a60e32860608737f1", "entry": "kid", "type": "normal", "definitions": [{"isInformal": null, "isVulgar": "0", "definition": "young person", "thesRid": "10837", "pos": "noun", "synonyms": [{"similarity": "100", "isInformal": "0", "isVulgar": null, "term": "boy", "targetTerm": "boy", "targetSlug": "boy"}, {"similarity": "100", "isInformal": "0", "isVulgar": null, "term": "infant", "targetTerm": "infant", "targetSlug": "infant"}, {"similarity": "100", "isInformal": "0", "isVulgar": null, "term": "daughter", "targetTerm": "daughter", "targetSlug": "daughter"}, {"similarity": "100", "isInformal": "0", "isVulgar": null, "term": "son", "targetTerm": "son", "targetSlug": "son"}, {"similarity": "100", "isInformal": "0", "isVulgar": null, "term": "youth", "targetTerm": "youth", "targetSlug": "youth"}, {"similarity": "100", "isInformal": "0", "isVulgar": null, "term": "teenager", "targetTerm": "teenager", "targetSlug": "teenager"}, {"similarity": "100", "isInformal": "0", "isVulgar": null, "term": "child", "targetTerm": "child", "targetSlug": "child"}, {"similarity": "100", "isInformal": "0", "isVulgar": null, "term": "baby", "targetTerm": "baby", "targetSlug": "baby"}, {"similarity": "100", "isInformal": "0", "isVulgar": null, "term": "girl", "targetTerm": "girl", "targetSlug": "girl"}, {"similarity": "100", "isInformal": "0", "isVulgar": null, "term": "youngster", "targetTerm": "youngster", "targetSlug": "youngster"}, {"similarity": "50", "isInformal": "0", "isVulgar": null, "term": "lad", "targetTerm": "lad", "targetSlug": "lad"}, {"similarity": "50", "isInformal": "0", "isVulgar": null, "term": "bairn", "targetTerm": "bairn", "targetSlug": "bairn"}, {"similarity": "50", "isInformal": "0", "isVulgar": null, "term": "juvenile", "targetTerm": "juvenile", "targetSlug": "juvenile"}, {"similarity": "50", "isInformal": "0", "isVulgar": null, "term": "lass", "targetTerm": "lass", "targetSlug": "lass"}, {"similarity": "50", "isInformal": "0", "isVulgar": null, "term": "tot", "targetTerm": "tot", "targetSlug": "tot"}, {"similarity": "10", "isInformal": "0", "isVulgar": null, "term": "little one", "targetTerm": "little one", "targetSlug": "little%20one"}], "antonyms": [{"similarity": "-100", "isInformal": "0", "isVulgar": null, "term": "adult", "targetTerm": "adult", "targetSlug": "adult"}], "note": null}, {"isInformal": null, "isVulgar": "0", "definition": "fool, ridicule", "thesRid": "10838", "pos": "verb", "synonyms": [{"similarity": "100", "isInformal": "0", "isVulgar": null, "term": "joke", "targetTerm": "joke", "targetSlug": "joke"}, {"similarity": "100", "isInformal": "0", "isVulgar": null, "term": "bother", "targetTerm": "bother", "targetSlug": "bother"}, {"similarity": "100", "isInformal": "0", "isVulgar": null, "term": "tease", "targetTerm": "tease", "targetSlug": "tease"}, {"similarity": "100", "isInformal": "0", "isVulgar": null, "term": "pretend", "targetTerm": "pretend", "targetSlug": "pretend"}, {"similarity": "100", "isInformal": "0", "isVulgar": null, "term": "delude", "targetTerm": "delude", "targetSlug": "delude"}, {"similarity": "50", "isInformal": "0", "isVulgar": null, "term": "flimflam", "targetTerm": "flimflam", "targetSlug": "flimflam"}, {"similarity": "50", "isInformal": "0", "isVulgar": null, "term": "rag", "targetTerm": "rag", "targetSlug": "rag"}, {"similarity": "50", "isInformal": "0", "isVulgar": null, "term": "razz", "targetTerm": "razz", "targetSlug": "razz"}, {"similarity": "50", "isInformal": "0", "isVulgar": null, "term": "jest", "targetTerm": "jest", "targetSlug": "jest"}, {"similarity": "50", "isInformal": "0", "isVulgar": null, "term": "jape", "targetTerm": "jape", "targetSlug": "jape"}, {"similarity": "50", "isInformal": "0", "isVulgar": null, "term": "hoax", "targetTerm": "hoax", "targetSlug": "hoax"}, {"similarity": "50", "isInformal": "0", "isVulgar": null, "term": "josh", "targetTerm": "josh", "targetSlug": "josh"}, {"similarity": "50", "isInformal": "0", "isVulgar": null, "term": "banter", "targetTerm": "banter", "targetSlug": "banter"}, {"similarity": "50", "isInformal": "0", "isVulgar": null, "term": "cozen", "targetTerm": "cozen", "targetSlug": "cozen"}, {"similarity": "50", "isInformal": "0", "isVulgar": null, "term": "gull", "targetTerm": "gull", "targetSlug": "gull"}, {"similarity": "50", "isInformal": "0", "isVulgar": null, "term": "jolly", "targetTerm": "jolly", "targetSlug": "jolly"}, {"similarity": "50", "isInformal": "0", "isVulgar": null, "term": "dupe", "targetTerm": "dupe", "targetSlug": "dupe"}, {"similarity": "50", "isInformal": "0", "isVulgar": null, "term": "trick", "targetTerm": "trick", "targetSlug": "trick"}, {"similarity": "50", "isInformal": "0", "isVulgar": null, "term": "beguile", "targetTerm": "beguile", "targetSlug": "beguile"}, {"similarity": "50", "isInformal": "1", "isVulgar": null, "term": "bamboozle", "targetTerm": "bamboozle", "targetSlug": "bamboozle"}, {"similarity": "50", "isInformal": "0", "isVulgar": null, "term": "roast", "targetTerm": "roast", "targetSlug": "roast"}, {"similarity": "50", "isInformal": "1", "isVulgar": null, "term": "fun", "targetTerm": "fun", "targetSlug": "fun"}, {"similarity": "50", "isInformal": "0", "isVulgar": null, "term": "spoof", "targetTerm": "spoof", "targetSlug": "spoof"}, {"similarity": "50", "isInformal": "0", "isVulgar": null, "term": "hoodwink", "targetTerm": "hoodwink", "targetSlug": "hoodwink"}, {"similarity": "50", "isInformal": "0", "isVulgar": null, "term": "rib", "targetTerm": "rib", "targetSlug": "rib"}, {"similarity": "50", "isInformal": "0", "isVulgar": null, "term": "mock", "targetTerm": "mock", "targetSlug": "mock"}, {"similarity": "10", "isInformal": "0", "isVulgar": null, "term": "make fun of", "targetTerm": "make fun of", "targetSlug": "make%20fun%20of"}, {"similarity": "10", "isInformal": "0", "isVulgar": null, "term": "make sport of", "targetTerm": "make sport of", "targetSlug": "make%20sport%20of"}], "antonyms": [{"similarity": "-10", "isInformal": "0", "isVulgar": null, "term": "be serious", "targetTerm": null, "targetSlug": null}], "note": null}], "slug": "kid"}, "categoryId": "348", "inflections": [{"displayForm": "kidding", "slug": "kidding"}, {"displayForm": "kids", "slug": "kids"}], "pronunciation": {"ipa": "k\u026ad ", "spell": "kid ", "audio": {"audio/ogg": "https://static.sfdict.com/audio/lunawav/K00/K0096500.ogg", "audio/mpeg": "https://static.sfdict.com/audio/K00/K0096500.mp3"}}, "confusables": [], "supplementaryNotes": [], "etymology": [], "exampleSentences": [{"source": {"url": "https://singularityhub.com/2021/02/26/the-worlds-first-3d-printed-school-will-be-built-in-madagascar/", "publication_date": "2021-02-26T15:00:55Z", "author": "Vanessa Bates Ramirez", "source_name": "Singularity Hub\u00a0", "title": "The World\u2019s First 3D Printed School Will Be Built in Madagascar", "type": "const", "abbreviation": "nlp"}, "profanity": 0, "id": 36744602, "sentence": "For people to feel good about sending their kids to school each day, the buildings should be conveniently located, appealing, comfortable to spend several hours in, and of course safe."}, {"source": {"url": "https://www.washingtonpost.com/lifestyle/2021/02/26/self-cyberbullying-digital-self-harm/", "publication_date": "2021-02-26T14:00:20Z", "author": "Juli Fraga", "source_name": "Washington Post", "title": "Digital self-harm: What to do when kids cyberbully themselves", "type": "const", "abbreviation": "nlp"}, "profanity": 0, "id": 36745188, "sentence": "Turban shares that kids who feel controlled or shamed are less likely to be forthcoming about potentially risky online behaviors."}, {"source": {"url": "https://www.voiceofsandiego.org/topics/news/morning-report-did-mexico-solve-the-border-sewage-problem/", "publication_date": "2021-02-26T12:30:32Z", "author": "Voice of San Diego", "source_name": "Voice of San Diego", "title": "Morning Report: Did Mexico Solve the Border Sewage Problem?", "type": "const", "abbreviation": "nlp"}, "profanity": 0, "id": 36743212, "sentence": "It would let the team compare how kids who attended quality-rate preschools did on their reading and math tests through their senior year of high school, compared to those who didn\u2019t."}, {"source": {"url": "https://www.washingtonpost.com/lifestyle/advice/hints-from-heloise-falling-for-a-scam-can-be-as-simple-as-saying-yes/2021/02/26/a79a20a6-6e7d-11eb-ba56-d7e2c8defa31_story.html", "publication_date": "2021-02-26T05:00:00Z", "author": "Heloise Heloise", "source_name": "Washington Post", "title": "Hints From Heloise: Falling for a scam can be as simple as saying \u2018yes\u2019", "type": "const", "abbreviation": "nlp"}, "profanity": 0, "id": 36745368, "sentence": "Hearing a kid rant or shout in a store reflects poorly on the parents, not the child."}, {"source": {"url": "https://www.sciencenews.org/article/coronavirus-covid-19-vaccines-children-kids-teens-ready-summer", "publication_date": "2021-02-25T22:08:03Z", "author": "Aimee Cunningham", "source_name": "Science News", "title": "COVID-19 vaccines may be ready for teens this summer", "type": "const", "abbreviation": "nlp"}, "profanity": 0, "id": 36741841, "sentence": "Proving the shots are safe and effective for children is a crucial first step to vaccinating this population and protecting kids\u2019 health."}, {"source": {"url": "https://fivethirtyeight.com/features/this-champions-league-round-has-not-been-kind-to-barcelona/", "publication_date": "2021-02-25T18:46:47Z", "author": "Chadwick Matlin (chadwick.matlin@fivethirtyeight.com)", "source_name": "FiveThirtyEight", "title": "This Champions League Round Has Not Been Kind To Barcelona", "type": "const", "abbreviation": "nlp"}, "profanity": 0, "id": 36744389, "sentence": "I\u2019ll admit I was half watching the game and half watching my kid, but it seemed like everytime I looked up at the TV, Isco or even Luka Modri\u0107 was making a run into the box, but Toni Kroos and Casemiro just couldn\u2019t find them."}, {"source": {"url": "https://www.washingtonpost.com/lifestyle/advice/miss-manners-get-out-of-dodge-before-the-abusive-mother-in-law-visits/2021/02/22/7101c194-6765-11eb-8468-21bc48f07fe5_story.html", "publication_date": "2021-02-25T05:00:00Z", "author": "Judith Martin, Nicholas Martin, Jacobina Martin", "source_name": "Washington Post", "title": "Miss Manners: Get out of Dodge before the abusive mother-in-law visits", "type": "const", "abbreviation": "nlp"}, "profanity": 0, "id": 36745992, "sentence": "Our adult kids refuse to see her because of the way she treats me, which is not my wish, nor do I want to be the cause of a rift between my husband and his mother."}, {"source": {"url": "https://freakonomics.com/podcast/boring-rebroadcast/?utm_source=rss&utm_medium=rss&utm_campaign=boring-rebroadcast", "publication_date": "2021-02-25T04:00:57Z", "author": "Stephen J. Dubner", "source_name": "Freakonomics", "title": "Am I Boring You? (Ep. 225 Rebroadcast)", "type": "const", "abbreviation": "nlp"}, "profanity": 0, "id": 36743384, "sentence": "Like, all you can do is sit at the beach or swim at the beach, play with the kids a little bit."}, {"source": {"url": "https://time.com/5941833/punky-brewster-tv-reboots/", "publication_date": "2021-02-24T20:25:48Z", "author": "Judy Berman", "source_name": "Time", "title": "Punky Brewster Is Just the Latest Proof That Today's Kids Deserve Better Than \u201880s and \u201890s Reboots", "type": "const", "abbreviation": "nlp"}, "profanity": 0, "id": 36739705, "sentence": "They speak to what is happening in kids\u2019 lives now and to everything timeless about childhood and adolescence."}, {"source": {"url": "https://www.popsci.com/story/reviews/best-science-gifts-for-kids/", "publication_date": "2021-02-18T17:02:20Z", "author": "PopSci Commerce Team", "source_name": "Popular Science", "title": "Toys and science gifts for kids of all ages", "type": "const", "abbreviation": "nlp"}, "profanity": 0, "id": 36728694, "sentence": "When in doubt, go classicSometimes it seems like all kid\u2019s toys are licensed and branded."}], "slugLuna": "kid"}