{"definitionData": {"_id": "60ad739060e3286060874789", "entry": "mean", "type": "normal", "definitions": [{"isInformal": null, "isVulgar": "0", "definition": "ungenerous", "thesRid": "11833", "pos": "adjective", "synonyms": [{"similarity": "100", "isInformal": "0", "isVulgar": null, "term": "selfish", "targetTerm": "selfish", "targetSlug": "selfish"}, {"similarity": "100", "isInformal": "0", "isVulgar": null, "term": "greedy", "targetTerm": "greedy", "targetSlug": "greedy"}, {"similarity": "50", "isInformal": "0", "isVulgar": null, "term": "close", "targetTerm": "close", "targetSlug": "close"}, {"similarity": "50", "isInformal": "0", "isVulgar": null, "term": "penny-pinching", "targetTerm": "penny-pinching", "targetSlug": "penny-pinching"}, {"similarity": "50", "isInformal": "0", "isVulgar": null, "term": "mercenary", "targetTerm": "mercenary", "targetSlug": "mercenary"}, {"similarity": "10", "isInformal": "0", "isVulgar": null, "term": "miserly", "targetTerm": "miserly", "targetSlug": "miserly"}, {"similarity": "10", "isInformal": "0", "isVulgar": null, "term": "parsimonious", "targetTerm": "parsimonious", "targetSlug": "parsimonious"}, {"similarity": "10", "isInformal": "0", "isVulgar": null, "term": "penurious", "targetTerm": "penurious", "targetSlug": "penurious"}, {"similarity": "10", "isInformal": "0", "isVulgar": null, "term": "rapacious", "targetTerm": "rapacious", "targetSlug": "rapacious"}, {"similarity": "10", "isInformal": "0", "isVulgar": null, "term": "stingy", "targetTerm": "stingy", "targetSlug": "stingy"}, {"similarity": "10", "isInformal": "0", "isVulgar": null, "term": "tight", "targetTerm": "tight", "targetSlug": "tight"}, {"similarity": "50", "isInformal": "0", "isVulgar": null, "term": "niggard", "targetTerm": "niggard", "targetSlug": "niggard"}, {"similarity": "10", "isInformal": "0", "isVulgar": null, "term": "mingy", "targetTerm": "mingy", "targetSlug": "mingy"}, {"similarity": "10", "isInformal": "0", "isVulgar": null, "term": "scrimpy", "targetTerm": "scrimpy", "targetSlug": "scrimpy"}, {"similarity": "10", "isInformal": "0", "isVulgar": null, "term": "tight-fisted", "targetTerm": "tight-fisted", "targetSlug": "tight-fisted"}], "antonyms": [{"similarity": "-10", "isInformal": "0", "isVulgar": null, "term": "extreme", "targetTerm": "extreme", "targetSlug": "extreme"}, {"similarity": "-10", "isInformal": "0", "isVulgar": null, "term": "sympathetic", "targetTerm": "sympathetic", "targetSlug": "sympathetic"}, {"similarity": "-10", "isInformal": "0", "isVulgar": null, "term": "noble", "targetTerm": "noble", "targetSlug": "noble"}, {"similarity": "-10", "isInformal": "0", "isVulgar": null, "term": "nice", "targetTerm": "nice", "targetSlug": "nice"}, {"similarity": "-50", "isInformal": "0", "isVulgar": null, "term": "generous", "targetTerm": "generous", "targetSlug": "generous"}, {"similarity": "-10", "isInformal": "0", "isVulgar": null, "term": "polite", "targetTerm": "polite", "targetSlug": "polite"}, {"similarity": "-10", "isInformal": "0", "isVulgar": null, "term": "compassionate", "targetTerm": "compassionate", "targetSlug": "compassionate"}, {"similarity": "-10", "isInformal": "0", "isVulgar": null, "term": "unselfish", "targetTerm": "unselfish", "targetSlug": "unselfish"}, {"similarity": "-10", "isInformal": "0", "isVulgar": null, "term": "kind", "targetTerm": "kind", "targetSlug": "kind"}], "note": null}, {"isInformal": null, "isVulgar": "0", "definition": "hostile, rude", "thesRid": "11834", "pos": "adjective", "synonyms": [{"similarity": "100", "isInformal": "0", "isVulgar": null, "term": "hard", "targetTerm": "hard", "targetSlug": "hard"}, {"similarity": "100", "isInformal": "0", "isVulgar": null, "term": "vile", "targetTerm": "vile", "targetSlug": "vile"}, {"similarity": "100", "isInformal": "0", "isVulgar": null, "term": "dangerous", "targetTerm": "dangerous", "targetSlug": "dangerous"}, {"similarity": "100", "isInformal": "0", "isVulgar": null, "term": "malicious", "targetTerm": "malicious", "targetSlug": "malicious"}, {"similarity": "100", "isInformal": "0", "isVulgar": null, "term": "callous", "targetTerm": "callous", "targetSlug": "callous"}, {"similarity": "100", "isInformal": "0", "isVulgar": null, "term": "vicious", "targetTerm": "vicious", "targetSlug": "vicious"}, {"similarity": "100", "isInformal": "0", "isVulgar": null, "term": "evil", "targetTerm": "evil", "targetSlug": "evil"}, {"similarity": "100", "isInformal": "0", "isVulgar": null, "term": "ugly", "targetTerm": "ugly", "targetSlug": "ugly"}, {"similarity": "100", "isInformal": "1", "isVulgar": null, "term": "dirty", "targetTerm": "dirty", "targetSlug": "dirty"}, {"similarity": "100", "isInformal": "0", "isVulgar": null, "term": "nasty", "targetTerm": "nasty", "targetSlug": "nasty"}, {"similarity": "100", "isInformal": "0", "isVulgar": null, "term": "rough", "targetTerm": "rough", "targetSlug": "rough"}, {"similarity": "50", "isInformal": "0", "isVulgar": null, "term": "touch", "targetTerm": "touch", "targetSlug": "touch"}, {"similarity": "50", "isInformal": "0", "isVulgar": null, "term": "sinking", "targetTerm": "sinking", "targetSlug": "sinking"}, {"similarity": "50", "isInformal": "0", "isVulgar": null, "term": "malign", "targetTerm": "malign", "targetSlug": "malign"}, {"similarity": "50", "isInformal": "0", "isVulgar": null, "term": "sour", "targetTerm": "sour", "targetSlug": "sour"}, {"similarity": "50", "isInformal": "1", "isVulgar": null, "term": "down", "targetTerm": "down", "targetSlug": "down"}, {"similarity": "10", "isInformal": "0", "isVulgar": null, "term": "bad-tempered", "targetTerm": "bad-tempered", "targetSlug": "bad-tempered"}, {"similarity": "10", "isInformal": "0", "isVulgar": null, "term": "cantankerous", "targetTerm": "cantankerous", "targetSlug": "cantankerous"}, {"similarity": "10", "isInformal": "0", "isVulgar": null, "term": "churlish", "targetTerm": "churlish", "targetSlug": "churlish"}, {"similarity": "10", "isInformal": "0", "isVulgar": null, "term": "contemptible", "targetTerm": "contemptible", "targetSlug": "contemptible"}, {"similarity": "10", "isInformal": "0", "isVulgar": null, "term": "despicable", "targetTerm": "despicable", "targetSlug": "despicable"}, {"similarity": "10", "isInformal": "0", "isVulgar": null, "term": "difficult", "targetTerm": "difficult", "targetSlug": "difficult"}, {"similarity": "10", "isInformal": "0", "isVulgar": null, "term": "disagreeable", "targetTerm": "disagreeable", "targetSlug": "disagreeable"}, {"similarity": "10", "isInformal": "0", "isVulgar": null, "term": "dishonorable", "targetTerm": "dishonorable", "targetSlug": "dishonorable"}, {"similarity": "10", "isInformal": "0", "isVulgar": null, "term": "formidable", "targetTerm": "formidable", "targetSlug": "formidable"}, {"similarity": "10", "isInformal": "0", "isVulgar": null, "term": "hard-nosed", "targetTerm": "hard-nosed", "targetSlug": "hard-nosed"}, {"similarity": "10", "isInformal": "0", "isVulgar": null, "term": "ignoble", "targetTerm": "ignoble", "targetSlug": "ignoble"}, {"similarity": "10", "isInformal": "0", "isVulgar": null, "term": "ill-tempered", "targetTerm": "ill-tempered", "targetSlug": "ill-tempered"}, {"similarity": "10", "isInformal": "0", "isVulgar": null, "term": "infamous", "targetTerm": "infamous", "targetSlug": "infamous"}, {"similarity": "10", "isInformal": "0", "isVulgar": null, "term": "knavish", "targetTerm": "knavish", "targetSlug": "knavish"}, {"similarity": "10", "isInformal": "1", "isVulgar": null, "term": "lousy", "targetTerm": "lousy", "targetSlug": "lousy"}, {"similarity": "10", "isInformal": "0", "isVulgar": null, "term": "perfidious", "targetTerm": "perfidious", "targetSlug": "perfidious"}, {"similarity": "10", "isInformal": "0", "isVulgar": null, "term": "pesky", "targetTerm": "pesky", "targetSlug": "pesky"}, {"similarity": "10", "isInformal": "0", "isVulgar": null, "term": "rotten", "targetTerm": "rotten", "targetSlug": "rotten"}, {"similarity": "10", "isInformal": "0", "isVulgar": null, "term": "rugged", "targetTerm": "rugged", "targetSlug": "rugged"}, {"similarity": "10", "isInformal": "0", "isVulgar": null, "term": "scurrilous", "targetTerm": "scurrilous", "targetSlug": "scurrilous"}, {"similarity": "10", "isInformal": "0", "isVulgar": null, "term": "shameless", "targetTerm": "shameless", "targetSlug": "shameless"}, {"similarity": "10", "isInformal": "0", "isVulgar": null, "term": "snide", "targetTerm": "snide", "targetSlug": "snide"}, {"similarity": "10", "isInformal": "0", "isVulgar": null, "term": "treacherous", "targetTerm": "treacherous", "targetSlug": "treacherous"}, {"similarity": "10", "isInformal": "0", "isVulgar": null, "term": "troublesome", "targetTerm": "troublesome", "targetSlug": "troublesome"}, {"similarity": "10", "isInformal": "0", "isVulgar": null, "term": "unfriendly", "targetTerm": "unfriendly", "targetSlug": "unfriendly"}, {"similarity": "10", "isInformal": "0", "isVulgar": null, "term": "unpleasant", "targetTerm": "unpleasant", "targetSlug": "unpleasant"}, {"similarity": "10", "isInformal": "0", "isVulgar": null, "term": "unscrupulous", "targetTerm": "unscrupulous", "targetSlug": "unscrupulous"}, {"similarity": "10", "isInformal": "0", "isVulgar": null, "term": "vexatious", "targetTerm": "vexatious", "targetSlug": "vexatious"}, {"similarity": "10", "isInformal": "0", "isVulgar": null, "term": "liverish", "targetTerm": "liverish", "targetSlug": "liverish"}, {"similarity": "10", "isInformal": "0", "isVulgar": null, "term": "low-down and dirty", "targetTerm": "low-down and dirty", "targetSlug": "low-down%20and%20dirty"}, {"similarity": "10", "isInformal": "0", "isVulgar": null, "term": "the lowest", "targetTerm": "the lowest", "targetSlug": "the%20lowest"}], "antonyms": [{"similarity": "-10", "isInformal": "0", "isVulgar": null, "term": "extreme", "targetTerm": "extreme", "targetSlug": "extreme"}, {"similarity": "-10", "isInformal": "0", "isVulgar": null, "term": "noble", "targetTerm": "noble", "targetSlug": "noble"}, {"similarity": "-10", "isInformal": "0", "isVulgar": null, "term": "generous", "targetTerm": "generous", "targetSlug": "generous"}, {"similarity": "-50", "isInformal": "0", "isVulgar": null, "term": "happy", "targetTerm": "happy", "targetSlug": "happy"}, {"similarity": "-100", "isInformal": "0", "isVulgar": null, "term": "clean", "targetTerm": "clean", "targetSlug": "clean"}, {"similarity": "-100", "isInformal": "0", "isVulgar": null, "term": "agreeable", "targetTerm": "agreeable", "targetSlug": "agreeable"}, {"similarity": "-100", "isInformal": "0", "isVulgar": null, "term": "upright", "targetTerm": "upright", "targetSlug": "upright"}, {"similarity": "-100", "isInformal": "0", "isVulgar": null, "term": "decent", "targetTerm": "decent", "targetSlug": "decent"}, {"similarity": "-100", "isInformal": "0", "isVulgar": null, "term": "good", "targetTerm": "good", "targetSlug": "good"}, {"similarity": "-100", "isInformal": "0", "isVulgar": null, "term": "safe", "targetTerm": "safe", "targetSlug": "safe"}, {"similarity": "-100", "isInformal": "0", "isVulgar": null, "term": "gentle", "targetTerm": "gentle", "targetSlug": "gentle"}, {"similarity": "-100", "isInformal": "0", "isVulgar": null, "term": "sympathetic", "targetTerm": "sympathetic", "targetSlug": "sympathetic"}, {"similarity": "-100", "isInformal": "0", "isVulgar": null, "term": "sensitive", "targetTerm": "sensitive", "targetSlug": "sensitive"}, {"similarity": "-100", "isInformal": "0", "isVulgar": null, "term": "nice", "targetTerm": "nice", "targetSlug": "nice"}, {"similarity": "-100", "isInformal": "0", "isVulgar": null, "term": "mild", "targetTerm": "mild", "targetSlug": "mild"}, {"similarity": "-10", "isInformal": "0", "isVulgar": null, "term": "polite", "targetTerm": "polite", "targetSlug": "polite"}, {"similarity": "-10", "isInformal": "0", "isVulgar": null, "term": "compassionate", "targetTerm": "compassionate", "targetSlug": "compassionate"}, {"similarity": "-10", "isInformal": "0", "isVulgar": null, "term": "unselfish", "targetTerm": "unselfish", "targetSlug": "unselfish"}, {"similarity": "-50", "isInformal": "0", "isVulgar": null, "term": "cheerful", "targetTerm": "cheerful", "targetSlug": "cheerful"}, {"similarity": "-100", "isInformal": "0", "isVulgar": null, "term": "pleasing", "targetTerm": "pleasing", "targetSlug": "pleasing"}, {"similarity": "-100", "isInformal": "0", "isVulgar": null, "term": "moral", "targetTerm": "moral", "targetSlug": "moral"}, {"similarity": "-100", "isInformal": "0", "isVulgar": null, "term": "friendly", "targetTerm": "friendly", "targetSlug": "friendly"}, {"similarity": "-100", "isInformal": "0", "isVulgar": null, "term": "kind", "targetTerm": "kind", "targetSlug": "kind"}, {"similarity": "-100", "isInformal": "0", "isVulgar": null, "term": "pleasant", "targetTerm": "pleasant", "targetSlug": "pleasant"}], "note": null}, {"isInformal": null, "isVulgar": "0", "definition": "poor; of or in inferior circumstances", "thesRid": "11835", "pos": "adjective", "synonyms": [{"similarity": "100", "isInformal": "0", "isVulgar": null, "term": "miserable", "targetTerm": "miserable", "targetSlug": "miserable"}, {"similarity": "100", "isInformal": "0", "isVulgar": null, "term": "vulgar", "targetTerm": "vulgar", "targetSlug": "vulgar"}, {"similarity": "100", "isInformal": "0", "isVulgar": null, "term": "petty", "targetTerm": "petty", "targetSlug": "petty"}, {"similarity": "100", "isInformal": "0", "isVulgar": null, "term": "humble", "targetTerm": "humble", "targetSlug": "humble"}, {"similarity": "50", "isInformal": "0", "isVulgar": null, "term": "limited", "targetTerm": "limited", "targetSlug": "limited"}, {"similarity": "50", "isInformal": "0", "isVulgar": null, "term": "plebeian", "targetTerm": "plebeian", "targetSlug": "plebeian"}, {"similarity": "50", "isInformal": "0", "isVulgar": null, "term": "menial", "targetTerm": "menial", "targetSlug": "menial"}, {"similarity": "50", "isInformal": "0", "isVulgar": null, "term": "base", "targetTerm": "base", "targetSlug": "base"}, {"similarity": "50", "isInformal": "0", "isVulgar": null, "term": "low", "targetTerm": "low", "targetSlug": "low"}, {"similarity": "50", "isInformal": "0", "isVulgar": null, "term": "hack", "targetTerm": "hack", "targetSlug": "hack"}, {"similarity": "50", "isInformal": "0", "isVulgar": null, "term": "obscure", "targetTerm": "obscure", "targetSlug": "obscure"}, {"similarity": "50", "isInformal": "0", "isVulgar": null, "term": "narrow", "targetTerm": "narrow", "targetSlug": "narrow"}, {"similarity": "50", "isInformal": "0", "isVulgar": null, "term": "ordinary", "targetTerm": "ordinary", "targetSlug": "ordinary"}, {"similarity": "50", "isInformal": "0", "isVulgar": null, "term": "inferior", "targetTerm": "inferior", "targetSlug": "inferior"}, {"similarity": "50", "isInformal": "0", "isVulgar": null, "term": "common", "targetTerm": "common", "targetSlug": "common"}, {"similarity": "10", "isInformal": "0", "isVulgar": null, "term": "beggarly", "targetTerm": "beggarly", "targetSlug": "beggarly"}, {"similarity": "10", "isInformal": "0", "isVulgar": null, "term": "contemptible", "targetTerm": "contemptible", "targetSlug": "contemptible"}, {"similarity": "10", "isInformal": "0", "isVulgar": null, "term": "ignoble", "targetTerm": "ignoble", "targetSlug": "ignoble"}, {"similarity": "10", "isInformal": "0", "isVulgar": null, "term": "ineffectual", "targetTerm": "ineffectual", "targetSlug": "ineffectual"}, {"similarity": "10", "isInformal": "0", "isVulgar": null, "term": "insignificant", "targetTerm": "insignificant", "targetSlug": "insignificant"}, {"similarity": "10", "isInformal": "0", "isVulgar": null, "term": "lowly", "targetTerm": "lowly", "targetSlug": "lowly"}, {"similarity": "10", "isInformal": "0", "isVulgar": null, "term": "mediocre", "targetTerm": "mediocre", "targetSlug": "mediocre"}, {"similarity": "10", "isInformal": "0", "isVulgar": null, "term": "modest", "targetTerm": "modest", "targetSlug": "modest"}, {"similarity": "10", "isInformal": "0", "isVulgar": null, "term": "paltry", "targetTerm": "paltry", "targetSlug": "paltry"}, {"similarity": "10", "isInformal": "0", "isVulgar": null, "term": "pitiful", "targetTerm": "pitiful", "targetSlug": "pitiful"}, {"similarity": "10", "isInformal": "0", "isVulgar": null, "term": "run-down", "targetTerm": "run-down", "targetSlug": "run-down"}, {"similarity": "10", "isInformal": "0", "isVulgar": null, "term": "scruffy", "targetTerm": "scruffy", "targetSlug": "scruffy"}, {"similarity": "10", "isInformal": "0", "isVulgar": null, "term": "second-rate", "targetTerm": "second-rate", "targetSlug": "second-rate"}, {"similarity": "10", "isInformal": "0", "isVulgar": null, "term": "seedy", "targetTerm": "seedy", "targetSlug": "seedy"}, {"similarity": "10", "isInformal": "0", "isVulgar": null, "term": "servile", "targetTerm": "servile", "targetSlug": "servile"}, {"similarity": "10", "isInformal": "1", "isVulgar": null, "term": "shabby", "targetTerm": "shabby", "targetSlug": "shabby"}, {"similarity": "10", "isInformal": "0", "isVulgar": null, "term": "sordid", "targetTerm": "sordid", "targetSlug": "sordid"}, {"similarity": "10", "isInformal": "0", "isVulgar": null, "term": "squalid", "targetTerm": "squalid", "targetSlug": "squalid"}, {"similarity": "10", "isInformal": "0", "isVulgar": null, "term": "tawdry", "targetTerm": "tawdry", "targetSlug": "tawdry"}, {"similarity": "10", "isInformal": "0", "isVulgar": null, "term": "undistinguished", "targetTerm": "undistinguished", "targetSlug": "undistinguished"}, {"similarity": "10", "isInformal": "0", "isVulgar": null, "term": "wretched", "targetTerm": "wretched", "targetSlug": "wretched"}, {"similarity": "10", "isInformal": "0", "isVulgar": null, "term": "d\u00e9class\u00e9", "targetTerm": "d\u00e9class\u00e9", "targetSlug": "d%C3%A9class%C3%A9"}, {"similarity": "10", "isInformal": "0", "isVulgar": null, "term": "second-class", "targetTerm": "second-class", "targetSlug": "second-class"}, {"similarity": "10", "isInformal": "0", "isVulgar": null, "term": "unwashed", "targetTerm": "unwashed", "targetSlug": "unwashed"}, {"similarity": "50", "isInformal": "0", "isVulgar": null, "term": "proletarian", "targetTerm": "proletarian", "targetSlug": "proletarian"}, {"similarity": "10", "isInformal": "0", "isVulgar": null, "term": "down-at-heel", "targetTerm": "down-at-heel", "targetSlug": "down-at-heel"}, {"similarity": "10", "isInformal": "0", "isVulgar": null, "term": "lowborn", "targetTerm": "lowborn", "targetSlug": "lowborn"}], "antonyms": [{"similarity": "-10", "isInformal": "0", "isVulgar": null, "term": "extreme", "targetTerm": "extreme", "targetSlug": "extreme"}, {"similarity": "-10", "isInformal": "0", "isVulgar": null, "term": "sympathetic", "targetTerm": "sympathetic", "targetSlug": "sympathetic"}, {"similarity": "-10", "isInformal": "0", "isVulgar": null, "term": "nice", "targetTerm": "nice", "targetSlug": "nice"}, {"similarity": "-10", "isInformal": "0", "isVulgar": null, "term": "generous", "targetTerm": "generous", "targetSlug": "generous"}, {"similarity": "-50", "isInformal": "0", "isVulgar": null, "term": "uncommon", "targetTerm": "uncommon", "targetSlug": "uncommon"}, {"similarity": "-50", "isInformal": "0", "isVulgar": null, "term": "high", "targetTerm": "high", "targetSlug": "high"}, {"similarity": "-50", "isInformal": "0", "isVulgar": null, "term": "superior", "targetTerm": "superior", "targetSlug": "superior"}, {"similarity": "-50", "isInformal": "0", "isVulgar": null, "term": "elevated", "targetTerm": "elevated", "targetSlug": "elevated"}, {"similarity": "-50", "isInformal": "0", "isVulgar": null, "term": "noble", "targetTerm": "noble", "targetSlug": "noble"}, {"similarity": "-100", "isInformal": "0", "isVulgar": null, "term": "rich", "targetTerm": "rich", "targetSlug": "rich"}, {"similarity": "-10", "isInformal": "0", "isVulgar": null, "term": "polite", "targetTerm": "polite", "targetSlug": "polite"}, {"similarity": "-10", "isInformal": "0", "isVulgar": null, "term": "compassionate", "targetTerm": "compassionate", "targetSlug": "compassionate"}, {"similarity": "-10", "isInformal": "0", "isVulgar": null, "term": "unselfish", "targetTerm": "unselfish", "targetSlug": "unselfish"}, {"similarity": "-10", "isInformal": "0", "isVulgar": null, "term": "kind", "targetTerm": "kind", "targetSlug": "kind"}, {"similarity": "-50", "isInformal": "0", "isVulgar": null, "term": "extraordinary", "targetTerm": "extraordinary", "targetSlug": "extraordinary"}, {"similarity": "-50", "isInformal": "0", "isVulgar": null, "term": "abnormal", "targetTerm": "abnormal", "targetSlug": "abnormal"}, {"similarity": "-50", "isInformal": "0", "isVulgar": null, "term": "moral", "targetTerm": "moral", "targetSlug": "moral"}, {"similarity": "-50", "isInformal": "0", "isVulgar": null, "term": "honest", "targetTerm": "honest", "targetSlug": "honest"}, {"similarity": "-50", "isInformal": "0", "isVulgar": null, "term": "aristocratic", "targetTerm": "aristocratic", "targetSlug": "aristocratic"}, {"similarity": "-50", "isInformal": "0", "isVulgar": null, "term": "unrestricted", "targetTerm": "unrestricted", "targetSlug": "unrestricted"}], "note": null}, {"isInformal": null, "isVulgar": "0", "definition": "average", "thesRid": "11837", "pos": "noun", "synonyms": [{"similarity": "50", "isInformal": "0", "isVulgar": null, "term": "par", "targetTerm": "par", "targetSlug": "par"}, {"similarity": "50", "isInformal": "0", "isVulgar": null, "term": "center", "targetTerm": "center", "targetSlug": "center"}, {"similarity": "50", "isInformal": "0", "isVulgar": null, "term": "midpoint", "targetTerm": "midpoint", "targetSlug": "midpoint"}, {"similarity": "50", "isInformal": "0", "isVulgar": null, "term": "median", "targetTerm": "median", "targetSlug": "median"}, {"similarity": "50", "isInformal": "0", "isVulgar": null, "term": "middle", "targetTerm": "middle", "targetSlug": "middle"}, {"similarity": "50", "isInformal": "0", "isVulgar": null, "term": "compromise", "targetTerm": "compromise", "targetSlug": "compromise"}, {"similarity": "50", "isInformal": "0", "isVulgar": null, "term": "balance", "targetTerm": "balance", "targetSlug": "balance"}, {"similarity": "50", "isInformal": "0", "isVulgar": null, "term": "norm", "targetTerm": "norm", "targetSlug": "norm"}, {"similarity": "10", "isInformal": "0", "isVulgar": null, "term": "happy medium", "targetTerm": "happy medium", "targetSlug": "happy%20medium"}, {"similarity": "10", "isInformal": "0", "isVulgar": null, "term": "middle course", "targetTerm": "middle course", "targetSlug": "middle%20course"}], "antonyms": [{"similarity": "-50", "isInformal": "0", "isVulgar": null, "term": "border", "targetTerm": "border", "targetSlug": "border"}, {"similarity": "-50", "isInformal": "0", "isVulgar": null, "term": "outside", "targetTerm": "outside", "targetSlug": "outside"}, {"similarity": "-50", "isInformal": "0", "isVulgar": null, "term": "margin", "targetTerm": "margin", "targetSlug": "margin"}, {"similarity": "-50", "isInformal": "0", "isVulgar": null, "term": "extreme", "targetTerm": "extreme", "targetSlug": "extreme"}], "note": null}, {"isInformal": null, "isVulgar": "0", "definition": "signify, convey", "thesRid": "11838", "pos": "verb", "synonyms": [{"similarity": "100", "isInformal": "0", "isVulgar": null, "term": "represent", "targetTerm": "represent", "targetSlug": "represent"}, {"similarity": "100", "isInformal": "0", "isVulgar": null, "term": "suggest", "targetTerm": "suggest", "targetSlug": "suggest"}, {"similarity": "100", "isInformal": "0", "isVulgar": null, "term": "spell", "targetTerm": "spell", "targetSlug": "spell"}, {"similarity": "100", "isInformal": "0", "isVulgar": null, "term": "say", "targetTerm": "say", "targetSlug": "say"}, {"similarity": "100", "isInformal": "0", "isVulgar": null, "term": "portend", "targetTerm": "portend", "targetSlug": "portend"}, {"similarity": "100", "isInformal": "0", "isVulgar": null, "term": "involve", "targetTerm": "involve", "targetSlug": "involve"}, {"similarity": "100", "isInformal": "0", "isVulgar": null, "term": "indicate", "targetTerm": "indicate", "targetSlug": "indicate"}, {"similarity": "100", "isInformal": "0", "isVulgar": null, "term": "imply", "targetTerm": "imply", "targetSlug": "imply"}, {"similarity": "100", "isInformal": "0", "isVulgar": null, "term": "promise", "targetTerm": "promise", "targetSlug": "promise"}, {"similarity": "100", "isInformal": "0", "isVulgar": null, "term": "determine", "targetTerm": "determine", "targetSlug": "determine"}, {"similarity": "50", "isInformal": "0", "isVulgar": null, "term": "herald", "targetTerm": "herald", "targetSlug": "herald"}, {"similarity": "50", "isInformal": "0", "isVulgar": null, "term": "argue", "targetTerm": "argue", "targetSlug": "argue"}, {"similarity": "50", "isInformal": "0", "isVulgar": null, "term": "name", "targetTerm": "name", "targetSlug": "name"}, {"similarity": "50", "isInformal": "0", "isVulgar": null, "term": "purport", "targetTerm": "purport", "targetSlug": "purport"}, {"similarity": "50", "isInformal": "0", "isVulgar": null, "term": "attest", "targetTerm": "attest", "targetSlug": "attest"}, {"similarity": "50", "isInformal": "0", "isVulgar": null, "term": "express", "targetTerm": "express", "targetSlug": "express"}, {"similarity": "50", "isInformal": "0", "isVulgar": null, "term": "betoken", "targetTerm": "betoken", "targetSlug": "betoken"}, {"similarity": "50", "isInformal": "0", "isVulgar": null, "term": "intimate", "targetTerm": "intimate", "targetSlug": "intimate"}, {"similarity": "50", "isInformal": "0", "isVulgar": null, "term": "denote", "targetTerm": "denote", "targetSlug": "denote"}, {"similarity": "50", "isInformal": "0", "isVulgar": null, "term": "foreshadow", "targetTerm": "foreshadow", "targetSlug": "foreshadow"}, {"similarity": "50", "isInformal": "0", "isVulgar": null, "term": "connote", "targetTerm": "connote", "targetSlug": "connote"}, {"similarity": "50", "isInformal": "0", "isVulgar": null, "term": "foretell", "targetTerm": "foretell", "targetSlug": "foretell"}, {"similarity": "50", "isInformal": "0", "isVulgar": null, "term": "adumbrate", "targetTerm": "adumbrate", "targetSlug": "adumbrate"}, {"similarity": "50", "isInformal": "0", "isVulgar": null, "term": "augur", "targetTerm": "augur", "targetSlug": "augur"}, {"similarity": "50", "isInformal": "0", "isVulgar": null, "term": "import", "targetTerm": "import", "targetSlug": "import"}, {"similarity": "50", "isInformal": "0", "isVulgar": null, "term": "symbolize", "targetTerm": "symbolize", "targetSlug": "symbolize"}, {"similarity": "50", "isInformal": "0", "isVulgar": null, "term": "presage", "targetTerm": "presage", "targetSlug": "presage"}, {"similarity": "50", "isInformal": "0", "isVulgar": null, "term": "allude", "targetTerm": "allude", "targetSlug": "allude"}, {"similarity": "50", "isInformal": "0", "isVulgar": null, "term": "designate", "targetTerm": "designate", "targetSlug": "designate"}, {"similarity": "10", "isInformal": "0", "isVulgar": null, "term": "drive at", "targetTerm": "drive at", "targetSlug": "drive%20at"}, {"similarity": "10", "isInformal": "0", "isVulgar": null, "term": "stand for", "targetTerm": "stand for", "targetSlug": "stand%20for"}, {"similarity": "10", "isInformal": "0", "isVulgar": null, "term": "add up", "targetTerm": "add up", "targetSlug": "add%20up"}, {"similarity": "10", "isInformal": "0", "isVulgar": null, "term": "allude to", "targetTerm": "allude to", "targetSlug": "allude%20to"}, {"similarity": "10", "isInformal": "0", "isVulgar": null, "term": "hint at", "targetTerm": "hint at", "targetSlug": "hint%20at"}, {"similarity": "10", "isInformal": "0", "isVulgar": null, "term": "point to", "targetTerm": "point to", "targetSlug": "point%20to"}, {"similarity": "10", "isInformal": "0", "isVulgar": null, "term": "speak of", "targetTerm": "speak of", "targetSlug": "speak%20of"}, {"similarity": "10", "isInformal": "0", "isVulgar": null, "term": "tell the meaning of", "targetTerm": "tell the meaning of", "targetSlug": "tell%20the%20meaning%20of"}, {"similarity": "10", "isInformal": "0", "isVulgar": null, "term": "touch on", "targetTerm": "touch on", "targetSlug": "touch%20on"}], "antonyms": [{"similarity": "-50", "isInformal": "0", "isVulgar": null, "term": "ignore", "targetTerm": "ignore", "targetSlug": "ignore"}], "note": null}, {"isInformal": null, "isVulgar": "0", "definition": "have in mind; intend", "thesRid": "11839", "pos": "verb", "synonyms": [{"similarity": "100", "isInformal": "0", "isVulgar": null, "term": "propose", "targetTerm": "propose", "targetSlug": "propose"}, {"similarity": "100", "isInformal": "0", "isVulgar": null, "term": "make", "targetTerm": "make", "targetSlug": "make"}, {"similarity": "100", "isInformal": "0", "isVulgar": null, "term": "aim", "targetTerm": "aim", "targetSlug": "aim"}, {"similarity": "100", "isInformal": "0", "isVulgar": null, "term": "design", "targetTerm": "design", "targetSlug": "design"}, {"similarity": "100", "isInformal": "0", "isVulgar": null, "term": "expect", "targetTerm": "expect", "targetSlug": "expect"}, {"similarity": "100", "isInformal": "0", "isVulgar": null, "term": "want", "targetTerm": "want", "targetSlug": "want"}, {"similarity": "100", "isInformal": "0", "isVulgar": null, "term": "anticipate", "targetTerm": "anticipate", "targetSlug": "anticipate"}, {"similarity": "100", "isInformal": "0", "isVulgar": null, "term": "plan", "targetTerm": "plan", "targetSlug": "plan"}, {"similarity": "50", "isInformal": "0", "isVulgar": null, "term": "desire", "targetTerm": "desire", "targetSlug": "desire"}, {"similarity": "50", "isInformal": "0", "isVulgar": null, "term": "resolve", "targetTerm": "resolve", "targetSlug": "resolve"}, {"similarity": "50", "isInformal": "0", "isVulgar": null, "term": "fit", "targetTerm": "fit", "targetSlug": "fit"}, {"similarity": "50", "isInformal": "0", "isVulgar": null, "term": "fate", "targetTerm": "fate", "targetSlug": "fate"}, {"similarity": "50", "isInformal": "0", "isVulgar": null, "term": "wish", "targetTerm": "wish", "targetSlug": "wish"}, {"similarity": "50", "isInformal": "0", "isVulgar": null, "term": "direct", "targetTerm": "direct", "targetSlug": "direct"}, {"similarity": "50", "isInformal": "0", "isVulgar": null, "term": "predestine", "targetTerm": "predestine", "targetSlug": "predestine"}, {"similarity": "50", "isInformal": "0", "isVulgar": null, "term": "preordain", "targetTerm": "preordain", "targetSlug": "preordain"}, {"similarity": "50", "isInformal": "0", "isVulgar": null, "term": "contemplate", "targetTerm": "contemplate", "targetSlug": "contemplate"}, {"similarity": "50", "isInformal": "0", "isVulgar": null, "term": "purpose", "targetTerm": "purpose", "targetSlug": "purpose"}, {"similarity": "50", "isInformal": "0", "isVulgar": null, "term": "suit", "targetTerm": "suit", "targetSlug": "suit"}, {"similarity": "50", "isInformal": "0", "isVulgar": null, "term": "aspire", "targetTerm": "aspire", "targetSlug": "aspire"}, {"similarity": "50", "isInformal": "0", "isVulgar": null, "term": "destine", "targetTerm": "destine", "targetSlug": "destine"}, {"similarity": "50", "isInformal": "0", "isVulgar": null, "term": "match", "targetTerm": "match", "targetSlug": "match"}, {"similarity": "10", "isInformal": "0", "isVulgar": null, "term": "set out", "targetTerm": "set out", "targetSlug": "set%20out"}], "antonyms": [{"similarity": "-50", "isInformal": "0", "isVulgar": null, "term": "neglect", "targetTerm": "neglect", "targetSlug": "neglect"}, {"similarity": "-100", "isInformal": "0", "isVulgar": null, "term": "refuse", "targetTerm": "refuse", "targetSlug": "refuse"}, {"similarity": "-100", "isInformal": "0", "isVulgar": null, "term": "deny", "targetTerm": "deny", "targetSlug": "deny"}], "note": null}], "slug": "mean"}, "inflections": [{"displayForm": "meaning", "slug": "meaning"}, {"displayForm": "means", "slug": "means"}, {"displayForm": "meant", "slug": "meant"}], "pronunciation": {"ipa": "min ", "spell": "meen ", "audio": {"audio/ogg": "https://static.sfdict.com/audio/lunawav/M02/M0243100.ogg", "audio/mpeg": "https://static.sfdict.com/audio/M02/M0243100.mp3"}}, "confusables": ["<span class=\"luna-form bold\">mean</span> , <a href=\"/browse/mien\" class=\"luna-xref\" data-linkid=\"nn1ov4\">mien</a>"], "supplementaryNotes": [], "etymology": [], "exampleSentences": [{"source": {"url": "https://www.outsideonline.com/2416446/6-family-friendly-adventures-try-summer?utm_campaign=rss&utm_source=rss&utm_medium=xmlfeed", "publication_date": "2020-09-17T16:32:40Z", "author": "Outside Editors", "source_name": "Outside Online", "title": "Three Family-Friendly Adventures to Try This Fall", "type": "const", "abbreviation": "nlp"}, "profanity": 0, "id": 36445248, "sentence": "The term \u201coff-roading\u201d means different things to different people."}, {"source": {"url": "https://www.washingtonpost.com/politics/2020/09/16/trump-blames-blue-states-coronavirus-death-toll-but-most-recent-deaths-have-been-red-states/", "publication_date": "2020-09-16T22:53:40Z", "author": "Philip Bump", "source_name": "Washington Post", "title": "Trump blames blue states for the coronavirus death toll \u2014\u00a0but most recent deaths have been in red states", "type": "const", "abbreviation": "nlp"}, "profanity": 0, "id": 36446705, "sentence": "The most recent data, through Tuesday, indicates that about 53 percent of deaths have occurred in blue states \u2014 meaning that 47 percent have occurred in red ones."}, {"source": {"url": "http://feeds.propublica.org/link/9499/13883259/propublicas-pandemic-guide-to-making-sure-your-vote-counts", "publication_date": "2020-09-16T22:39:00Z", "author": "by Susie Armitage", "source_name": "ProPublica", "title": "ProPublica\u2019s Pandemic Guide to Making Sure Your Vote Counts", "type": "const", "abbreviation": "nlp"}, "profanity": 0, "id": 36444692, "sentence": "Some states are also mandated to remove voters deemed \u201cinactive,\u201d meaning they didn\u2019t respond to a mailer sent to confirm their address and haven\u2019t voted in the last few elections."}, {"source": {"url": "https://www.washingtonpost.com/elections/2020/09/15/trump-biden-live-updates/", "publication_date": "2020-09-16T03:36:30Z", "author": "Colby Itkowitz, Josh Dawsey, Felicia Sonmez, John Wagner", "source_name": "Washington Post", "title": "Trump, in town hall, says he wouldn\u2019t have done anything differently on pandemic", "type": "const", "abbreviation": "nlp"}, "profanity": 0, "id": 36446975, "sentence": "I mean, I thought I\u2019d take it right off the table right this very minute."}, {"source": {"url": "http://feeds.propublica.org/link/9499/13879226/still-no-answers-to-lawmakers-questions-about-children-stuck-in-psychiatric-hospitals", "publication_date": "2020-09-15T14:41:00Z", "author": "by Duaa Eldeib", "source_name": "ProPublica", "title": "Still No Answers to Lawmakers\u2019 Questions About Children Stuck in Psychiatric Hospitals", "type": "const", "abbreviation": "nlp"}, "profanity": 0, "id": 36444850, "sentence": "One doctor said some patients attacked their peers or employees as a way to get out of the hospital, even if it meant going to jail."}, {"source": {"url": "https://digiday.com/marketing/deep-dive-how-the-summer-of-2020-forced-brand-marketing-to-change-for-the-better/", "publication_date": "2020-09-14T04:01:08Z", "author": "jim cooper", "source_name": "Digiday", "title": "Deep Dive: How the Summer of 2020 forced brand marketing to change for the better", "type": "const", "abbreviation": "nlp"}, "profanity": 0, "id": 36445764, "sentence": "It just means the ability to continually become the most powerful and relevant version of you and your proposition, your experience."}, {"source": {"url": "https://fortune.com/2020/09/12/americas-national-debt-servicing-costs-cheaper-covid-stimulus-coronavirus/", "publication_date": "2020-09-12T16:00:54Z", "author": "McKenna Moore", "source_name": "Fortune", "title": "America\u2019s $20 trillion debt is getting cheaper as it grows", "type": "const", "abbreviation": "nlp"}, "profanity": 0, "id": 36444174, "sentence": "\u201cIt means that the Fed can keep going with very cheap money, that it can go on for a much longer time at this rate,\u201d he said."}, {"source": {"url": "https://fortune.com/2020/09/12/changing-habits-environmental-cues-moving-vacation-covid-19/", "publication_date": "2020-09-12T15:00:00Z", "author": "matthewheimer", "source_name": "Fortune", "title": "How a vacation\u2014or a pandemic\u2014can help you adopt better habits now", "type": "const", "abbreviation": "nlp"}, "profanity": 0, "id": 36444230, "sentence": "Given the pandemic, many people are working from home\u2014but this means you can really work from anywhere."}, {"source": {"url": "https://fortune.com/2020/09/12/interruption-insurance-covid-19-lawsuits/", "publication_date": "2020-09-12T10:00:00Z", "author": "Bernhard Warner", "source_name": "Fortune", "title": "Got interruption insurance? These companies found it\u2019s useless in the age of COVID-19", "type": "const", "abbreviation": "nlp"}, "profanity": 0, "id": 36444303, "sentence": "That means courts in October and November will likely start deciding just how much, if any, property has been damaged by the coronavirus, he said."}, {"sentence": "Hilda, trembling at the door, more than half expected Mr. Orgreave to say: \"You mean, she's invited herself.\"", "profanity": 0, "source": {"title": "Hilda Lessways", "type": "const", "url": "http://www.gutenberg.org/files/10658/10658-h/10658-h.htm", "author": "Arnold Bennett", "publication_date": null, "abbreviation": "gbg"}, "id": "tXcqLncBoaa-DHVhCdAT"}], "slugLuna": "mean"}